systemsim/__init__.py
systemsim/core.py
systemsim/linear.py
systemsim/mechanical.py
systemsim/network.py
systemsim/symbolic.py
systemsim-0.22.dist-info/DESCRIPTION.rst
systemsim-0.22.dist-info/METADATA
systemsim-0.22.dist-info/RECORD
systemsim-0.22.dist-info/WHEEL
systemsim-0.22.dist-info/metadata.json
systemsim-0.22.dist-info/top_level.txt
