Metadata-Version: 2.0
Name: systemsim
Version: 0.22
Summary: Simulator for dynamical feedback systems and networks.
Home-page: https://github.com/laurensvalk/systemsim
Author: Laurens Valk
Author-email: laurensvalk@gmail.com
License: UNKNOWN
Keywords: dynamics simulation control
Platform: UNKNOWN
Classifier: Development Status :: 3 - Alpha
Classifier: License :: OSI Approved :: MIT License
Classifier: Programming Language :: Python :: 3
Requires-Python: >=3
